dissect_deconv/__init__.py
dissect_deconv/dissect_expr.py
dissect_deconv/dissect_frac.py
dissect_deconv/prepare_data.py
dissect_deconv/PropsSimulator/__init__.py
dissect_deconv/PropsSimulator/simulator.cpython-38-darwin.so
dissect_deconv/PropsSimulator/simulator.py
dissect_deconv/configs/__init__.py
dissect_deconv/configs/config.py
dissect_deconv/utils/__init__.py
dissect_deconv/utils/network_fn.py
dissect_deconv/utils/utils_fn.py
dissect_deconv/utils/utils_fn_others.py
dissect_deconv-0.1.dist-info/LICENSE
dissect_deconv-0.1.dist-info/METADATA
dissect_deconv-0.1.dist-info/WHEEL
dissect_deconv-0.1.dist-info/top_level.txt
dissect_deconv-0.1.dist-info/RECORD
