Metadata-Version: 2.1
Name: dissect-deconv
Version: 0.1
Summary: UNKNOWN
Home-page: https://github.com/imsb-uke/DISSECT
Author: Robin Khatri
Author-email: robin.khatri@zmnh.uni-hamburg.de
License: MIT License
Keywords: bioinformatics,deep learning,machine learning,single cell sequencing,bulk rna sequencing,spatial transcriptomics,deconvolution
Platform: UNKNOWN
Requires-Python: >=3.8.6
License-File: LICENSE
Requires-Dist: numpy (>=1.19.5)
Requires-Dist: scikit-learn (>=1.1.2)
Requires-Dist: pandas (>=1.4.3)
Requires-Dist: anndata (>=0.8.0)
Requires-Dist: h5py (>=3.6.0)
Requires-Dist: scanpy (>=1.9.1)
Requires-Dist: shap (>=0.40.0)
Requires-Dist: Cython (>=0.29.28)
Requires-Dist: matplotlib (>=3.5.0)
Requires-Dist: setuptools (>=59.4.0)
Requires-Dist: tqdm (>=4.62.3)
